<annotation>
	<folder>trainImage</folder>
	<filename>028.jpg</filename>
	<path>/devdata/darknet/trainImage/028.jpg</path>
	<source>
		<database>Unknown</database>
	</source>
	<size>
		<width>1023</width>
		<height>682</height>
		<depth>3</depth>
	</size>
	<segmented>0</segmented>
	<object>
		<name>bus</name>
		<pose>Unspecified</pose>
		<truncated>0</truncated>
		<difficult>0</difficult>
		<bndbox>
			<xmin>191</xmin>
			<ymin>295</ymin>
			<xmax>931</xmax>
			<ymax>515</ymax>
		</bndbox>
	</object>
</annotation>
